{"itinerary": [{"match_id": "22", "kickoff_utc": "2026-06-17 20:00:00+00:00", "team_a": "England", "team_b": "Croatia", "city": "dallas", "stage": "group-stage", "lat": 32.73024043, "lon": -97.08025844, "travel_distance": 1518.03, "travel_duration": 17.92}, {"match_id": "45", "kickoff_utc": "2026-06-23 20:00:00+00:00", "team_a": "England", "team_b": "Ghana", "city": "boston", "stage": "group-stage", "lat": 42.09082382, "lon": -71.26455613, "travel_distance": 2845.67, "travel_duration": 32.88}, {"match_id": "67", "kickoff_utc": "2026-06-27 21:00:00+00:00", "team_a": "Panama", "team_b": "England", "city": "new-york", "stage": "group-stage", "lat": 40.82236901, "lon": -74.07995734, "travel_distance": 331.17, "travel_duration": 4.42}, {"match_id": "86", "kickoff_utc": "2026-07-03 22:00:00+00:00", "team_a": "Group J winners", "team_b": "Group H runners-up", "city": "miami", "stage": "round-of-32", "lat": 25.9581328, "lon": -80.23888966, "travel_distance": 2036.94, "travel_duration": 23.81}, {"match_id": "95", "kickoff_utc": "2026-07-07 16:00:00+00:00", "team_a": "Winner Match 86", "team_b": "Winner Match 88", "city": "atlanta", "stage": "round-of-16", "lat": 33.75748929, "lon": -84.40044532, "travel_distance": 1044.79, "travel_duration": 11.83}, {"match_id": "100", "kickoff_utc": "2026-07-12 01:00:00+00:00", "team_a": "Winner Match 95", "team_b": "Winner Match 96", "city": "kansas-city", "stage": "quarter-finals", "lat": 39.04874353, "lon": -94.48187882, "travel_distance": 1278.01, "travel_duration": 14.85}, {"match_id": "102", "kickoff_utc": "2026-07-15 19:00:00+00:00", "team_a": "Winner Match 99", "team_b": "Winner Match 100", "city": "atlanta", "stage": "semi-finals", "lat": 33.75748929, "lon": -84.40044532, "travel_distance": 1275.5, "travel_duration": 14.77}, {"match_id": "104", "kickoff_utc": "2026-07-19 19:00:00+00:00", "team_a": "Winner Match 101", "team_b": "Winner Match 102", "city": "new-york", "stage": "final", "lat": 40.82236901, "lon": -74.07995734, "travel_distance": 1386.88, "travel_duration": 16.86}], "route_detail": [], "distance": 11.72, "duration": 11.72}